pulse/downloader/__init__.py
pulse/downloader/concat.py
pulse/downloader/flatten.py
pulse/downloader/pipeline.py
pulse/downloader/query.py
pulse/downloader/utils.py
ist_pulse_data_extractor-1.0.2.dist-info/LICENSE.txt
ist_pulse_data_extractor-1.0.2.dist-info/METADATA
ist_pulse_data_extractor-1.0.2.dist-info/WHEEL
ist_pulse_data_extractor-1.0.2.dist-info/top_level.txt
ist_pulse_data_extractor-1.0.2.dist-info/RECORD
