Metadata-Version: 2.1
Name: ist-pulse-data-extractor
Version: 1.0.2
Summary: Pulse Data Extractor
Home-page: https://github.com/istresearch/pulse-data-extractor
Author: Joe Goulet
Author-email: support@istresearch.com
License: UNKNOWN
Platform: UNKNOWN
Classifier: Programming Language :: Python :: 3.7
Classifier: License :: OSI Approved :: MIT License
Classifier: Operating System :: OS Independent
Requires-Dist: boto3
Requires-Dist: certifi
Requires-Dist: elasticsearch
Requires-Dist: loguru
Requires-Dist: pandas
Requires-Dist: pendulum
Requires-Dist: python-dotenv
Requires-Dist: ray
Requires-Dist: requests
